.babelrc
.eslintrc
CHANGES.rst
LICENSE
MANIFEST.in
README.rst
package.json
setup.cfg
setup.py
tox.ini
webpack.config.js
js/actions.js
js/components.jsx
js/container.js
js/foo.css
js/index.jsx
js/reducers.js
js/store.js
morepath_reactredux/__init__.py
morepath_reactredux/app.py
morepath_reactredux/fakedb.py
morepath_reactredux/model.py
morepath_reactredux/path.py
morepath_reactredux/run.py
morepath_reactredux/view.py
morepath_reactredux.egg-info/PKG-INFO
morepath_reactredux.egg-info/SOURCES.txt
morepath_reactredux.egg-info/dependency_links.txt
morepath_reactredux.egg-info/entry_points.txt
morepath_reactredux.egg-info/not-zip-safe
morepath_reactredux.egg-info/requires.txt
morepath_reactredux.egg-info/top_level.txt
morepath_reactredux/tests/__init__.py
morepath_reactredux/tests/test_rest.py
static/bundle.js
static/bundle.js.map
static/index.html